HexAeroPy/__init__.py
HexAeroPy/h3maps.py
HexAeroPy/runways.py
HexAeroPy/setup_module.py
HexAeroPy-1.0.4.dist-info/LICENSE
HexAeroPy-1.0.4.dist-info/METADATA
HexAeroPy-1.0.4.dist-info/WHEEL
HexAeroPy-1.0.4.dist-info/top_level.txt
HexAeroPy-1.0.4.dist-info/RECORD
