Metadata-Version: 2.1
Name: HexAeroPy
Version: 1.0.4
Summary: A EUROCONTROL package to determine used airports, runways, taxiways and stands based on flight trajectory coordinates.
Home-page: https://github.com/euctrl-pru/hexaeropy
Author: Quinten Goens
Author-email: quinten.goens@eurocontrol.int
License: MIT
Classifier: License :: OSI Approved :: MIT License
Classifier: Programming Language :: Python :: 3.9
Classifier: Programming Language :: Python :: 3.10
License-File: LICENSE
Requires-Dist: h3 >=3.7.6
Requires-Dist: pandas >=1.5.2
Requires-Dist: matplotlib >=3.6.3
Requires-Dist: geojson >=3.1.0
Requires-Dist: folium >=0.14.0
Requires-Dist: requests >=2.27.0
Requires-Dist: tqdm >=4.0.0
Requires-Dist: h3pandas >=0.2.6
